minimalkv/__init__.py
minimalkv/_boto.py
minimalkv/_constants.py
minimalkv/_get_store.py
minimalkv/_hstores.py
minimalkv/_key_value_store.py
minimalkv/_mixins.py
minimalkv/_store_creation.py
minimalkv/_store_decoration.py
minimalkv/_url_utils.py
minimalkv/_urls.py
minimalkv/cache.py
minimalkv/crypt.py
minimalkv/decorator.py
minimalkv/fs.py
minimalkv/fsspecstore.py
minimalkv/git.py
minimalkv/idgen.py
minimalkv/py.typed
minimalkv/contrib/__init__.py
minimalkv/db/__init__.py
minimalkv/db/mongo.py
minimalkv/db/sql.py
minimalkv/memory/__init__.py
minimalkv/memory/redisstore.py
minimalkv/net/__init__.py
minimalkv/net/_aws_refreshable_session.py
minimalkv/net/_azurestore_common.py
minimalkv/net/_azurestore_new.py
minimalkv/net/_azurestore_old.py
minimalkv/net/_net_common.py
minimalkv/net/azurestore.py
minimalkv/net/boto3store.py
minimalkv/net/botostore.py
minimalkv/net/gcstore.py
minimalkv/net/s3fsstore.py
minimalkv-1.11.2.dist-info/AUTHORS
minimalkv-1.11.2.dist-info/LICENSE
minimalkv-1.11.2.dist-info/METADATA
minimalkv-1.11.2.dist-info/WHEEL
minimalkv-1.11.2.dist-info/top_level.txt
minimalkv-1.11.2.dist-info/RECORD
