Metadata-Version: 2.1
Name: minimalkv
Version: 1.11.2
Summary: A key-value storage for binary data, support many backends.
Author-email: Data Engineering Collective <minimalkv@uwekorn.com>
License: Copyright (c) 2021, The minimal kv contributors
Project-URL: repository, https://github.com/data-engineering-collective/minimalkv
Classifier: License :: OSI Approved :: BSD License
Classifier: Programming Language :: Python :: 3
Classifier: Programming Language :: Python :: 3.9
Classifier: Programming Language :: Python :: 3.10
Classifier: Programming Language :: Python :: 3.11
Classifier: Programming Language :: Python :: 3.12
Classifier: Development Status :: 5 - Production/Stable
Classifier: Operating System :: OS Independent
Requires-Python: >=3.9
License-File: LICENSE
License-File: AUTHORS
Requires-Dist: uritools
